imagesize.py
imagesize-1.4.0.dist-info/LICENSE.rst
imagesize-1.4.0.dist-info/METADATA
imagesize-1.4.0.dist-info/WHEEL
imagesize-1.4.0.dist-info/top_level.txt
imagesize-1.4.0.dist-info/RECORD
